stewchef/__init__.py
stewchef/main.py
stewchef-0.1.5.dist-info/METADATA
stewchef-0.1.5.dist-info/WHEEL
stewchef-0.1.5.dist-info/entry_points.txt
stewchef-0.1.5.dist-info/RECORD
