Metadata-Version: 2.1
Name: stewchef
Version: 0.1.5
Summary: A MediaWiki API wrapper for RegiSoup
Author: pengu5055
Author-email: urbancmarko1@gmail.com
Requires-Python: >=3.7,<4.0
Classifier: Programming Language :: Python :: 3
Classifier: Programming Language :: Python :: 3.7
Classifier: Programming Language :: Python :: 3.8
Classifier: Programming Language :: Python :: 3.9
Classifier: Programming Language :: Python :: 3.10
Classifier: Programming Language :: Python :: 3.11
Requires-Dist: beautifulsoup4 (>=4.12.1,<5.0.0)
Requires-Dist: regisoup (>=0.1.10,<0.2.0)
Requires-Dist: requests (>=2.28.2,<3.0.0)
Requires-Dist: toml (>=0.10.2,<0.11.0)
Requires-Dist: tomli (>=2.0.1,<3.0.0)
Requires-Dist: typer[all] (>=0.7.0,<0.8.0)
